{
  "id": "task-d026ad3f-6af4-4778-b447-2a58b2d82d81",
  "ownerCommand": "1. Build the durable store\n2. Build the engine\n3. Wire the API",
  "originalTask": "1. Build the durable store\n2. Build the engine\n3. Wire the API",
  "status": "BUILT_NOT_DEPLOYED",
  "createdAt": "2026-07-08T01:16:14.379Z",
  "updatedAt": "2026-07-08T01:16:14.417Z",
  "completedAt": "2026-07-08T01:16:14.417Z",
  "currentBlockIndex": 3,
  "currentBlockId": null,
  "totalBlocks": 3,
  "completedBlockIds": [
    "task-d026ad3f-6af4-4778-b447-2a58b2d82d81-b1",
    "task-d026ad3f-6af4-4778-b447-2a58b2d82d81-b2",
    "task-d026ad3f-6af4-4778-b447-2a58b2d82d81-b3"
  ],
  "failedBlockIds": [],
  "blockedBlockIds": [],
  "deploymentStatus": "verified",
  "error": null,
  "lastCrash": {
    "at": "2026-07-08T01:16:14.398Z",
    "detail": "simulated crash mid-block",
    "blockId": "task-d026ad3f-6af4-4778-b447-2a58b2d82d81-b1"
  },
  "recoveryCount": 1,
  "statusMigration": {
    "from": "completed",
    "to": "BUILT_NOT_DEPLOYED",
    "reason": "Fake completed replaced per owner directive: no code diff, no commit SHA, no GitHub push, no Render deploy, no production verification.",
    "migratedAt": "2026-07-08T03:25:00Z"
  }
}