[
  {
    "id": "task-3fe75bdc-3886-4da7-be3b-a4b16d5c0ab0-b1",
    "index": 0,
    "title": "Only block",
    "goal": "Test transitions",
    "filesInvolved": [],
    "status": "VERIFIED",
    "codeChanges": null,
    "codeDiff": null,
    "validationCommand": null,
    "testResult": "PASSED: 10 tests",
    "commitHash": "abc123def456",
    "deploymentStatus": null,
    "verification": {
      "endpoint": "https://api.ivxholding.com/health",
      "ok": true,
      "httpStatus": 200,
      "changedRouteOk": true,
      "verifiedAt": "2026-07-16T18:15:27.195Z"
    },
    "blocker": null,
    "nextBlockId": null,
    "attempts": 0,
    "error": null,
    "createdAt": "2026-07-16T18:15:27.189Z",
    "startedAt": "2026-07-16T18:15:27.190Z",
    "completedAt": "2026-07-16T18:15:27.195Z"
  }
]