{
  "id": "task-1ab0098f-00eb-46b9-a527-ab78f258bd99",
  "ownerCommand": "1. Build the durable store\n2. Build the engine\n3. Wire the API",
  "originalTask": "1. Build the durable store\n2. Build the engine\n3. Wire the API",
  "status": "blocked",
  "createdAt": "2026-07-05T16:13:37.994Z",
  "updatedAt": "2026-07-08T03:51:13.421Z",
  "completedAt": null,
  "currentBlockIndex": 3,
  "currentBlockId": null,
  "totalBlocks": 3,
  "completedBlockIds": [
    "task-1ab0098f-00eb-46b9-a527-ab78f258bd99-b1",
    "task-1ab0098f-00eb-46b9-a527-ab78f258bd99-b2",
    "task-1ab0098f-00eb-46b9-a527-ab78f258bd99-b3"
  ],
  "failedBlockIds": [],
  "blockedBlockIds": [],
  "deploymentStatus": null,
  "error": "MIGRATED: fake completed status — no real deploy/verification proof.",
  "lastCrash": null,
  "recoveryCount": 0
}