{
  "id": "task-27f3f807-fb58-404c-b891-e08ab154112e",
  "ownerCommand": "Failure test",
  "originalTask": "Failure test",
  "status": "failed",
  "createdAt": "2026-07-16T18:29:42.522Z",
  "updatedAt": "2026-07-16T18:29:42.536Z",
  "completedAt": null,
  "currentBlockIndex": 0,
  "currentBlockId": "task-27f3f807-fb58-404c-b891-e08ab154112e-b1",
  "totalBlocks": 1,
  "completedBlockIds": [],
  "failedBlockIds": [],
  "blockedBlockIds": [],
  "deploymentStatus": null,
  "error": "Deploy trigger returned HTTP 401: Invalid API key",
  "lastCrash": null,
  "recoveryCount": 0
}