[
  {
    "id": "task-7a7a4eb2-44f1-4f6d-974d-283573049404-b1",
    "index": 0,
    "title": "Block",
    "goal": "Test secret safety",
    "filesInvolved": [],
    "status": "PENDING",
    "codeChanges": null,
    "codeDiff": null,
    "validationCommand": null,
    "testResult": null,
    "commitHash": null,
    "deploymentStatus": null,
    "verification": null,
    "blocker": null,
    "nextBlockId": null,
    "attempts": 0,
    "error": null,
    "createdAt": "2026-07-16T18:49:14.244Z",
    "startedAt": null,
    "completedAt": null
  }
]