{
  "id": "task-5602cd78-5828-4a95-af4d-190bccea25e2",
  "ownerCommand": "Event ordering test",
  "originalTask": "Event ordering test",
  "status": "queued",
  "createdAt": "2026-07-16T18:15:23.686Z",
  "updatedAt": "2026-07-16T18:15:23.686Z",
  "completedAt": null,
  "currentBlockIndex": 0,
  "currentBlockId": "task-5602cd78-5828-4a95-af4d-190bccea25e2-b1",
  "totalBlocks": 1,
  "completedBlockIds": [],
  "failedBlockIds": [],
  "blockedBlockIds": [],
  "deploymentStatus": null,
  "error": null,
  "lastCrash": null,
  "recoveryCount": 0
}